function/__init__.py
function/news_keyword.py
function/news_summarization.py
function/news_text.py
function/news_url_import.py
SqueezeNews-0.0.1.dist-info/METADATA
SqueezeNews-0.0.1.dist-info/WHEEL
SqueezeNews-0.0.1.dist-info/top_level.txt
SqueezeNews-0.0.1.dist-info/RECORD
