Metadata-Version: 2.1
Name: SqueezeNews
Version: 0.0.1
Summary: SqueezeNews Package
Home-page: https://github.com/rmakerck37/SqueezeNews
Author: Group 4
Author-email: jjhh1545@gmail.com
License: Apache
Platform: UNKNOWN
Requires-Python: >=3
